{
    "os": "Linux-6.2.0-36-generic-x86_64-with-glibc2.29",
    "python": "3.8.10",
    "heartbeatAt": "2023-11-20T02:49:32.801077",
    "startedAt": "2023-11-20T02:49:32.011471",
    "docker": null,
    "cuda": null,
    "args": [],
    "state": "running",
    "program": "wandb_test.py",
    "codePathLocal": "wandb_test.py",
    "codePath": "wandb_test.py",
    "host": "449c0d7379e5",
    "username": "root",
    "executable": "/usr/bin/python3",
    "cpu_count": 16,
    "cpu_count_logical": 24,
    "cpu_freq": {
        "current": 4198.093125,
        "min": 800.0,
        "max": 4950.0
    },
    "cpu_freq_per_core": [
        {
            "current": 5299.857,
            "min": 800.0,
            "max": 5300.0
        },
        {
            "current": 3400.0,
            "min": 800.0,
            "max": 5300.0
        },
        {
            "current": 5300.0,
            "min": 800.0,
            "max": 5300.0
        },
        {
            "current": 3400.0,
            "min": 800.0,
            "max": 5300.0
        },
        {
            "current": 5300.0,
            "min": 800.0,
            "max": 5300.0
        },
        {
            "current": 3400.0,
            "min": 800.0,
            "max": 5300.0
        },
        {
            "current": 5300.0,
            "min": 800.0,
            "max": 5300.0
        },
        {
            "current": 3400.0,
            "min": 800.0,
            "max": 5300.0
        },
        {
            "current": 5300.0,
            "min": 800.0,
            "max": 5400.0
        },
        {
            "current": 3400.0,
            "min": 800.0,
            "max": 5400.0
        },
        {
            "current": 5300.0,
            "min": 800.0,
            "max": 5400.0
        },
        {
            "current": 3400.0,
            "min": 800.0,
            "max": 5400.0
        },
        {
            "current": 5300.0,
            "min": 800.0,
            "max": 5300.0
        },
        {
            "current": 3400.0,
            "min": 800.0,
            "max": 5300.0
        },
        {
            "current": 5300.0,
            "min": 800.0,
            "max": 5300.0
        },
        {
            "current": 3400.0,
            "min": 800.0,
            "max": 5300.0
        },
        {
            "current": 4199.749,
            "min": 800.0,
            "max": 4200.0
        },
        {
            "current": 4200.393,
            "min": 800.0,
            "max": 4200.0
        },
        {
            "current": 4199.993,
            "min": 800.0,
            "max": 4200.0
        },
        {
            "current": 3400.0,
            "min": 800.0,
            "max": 4200.0
        },
        {
            "current": 3400.0,
            "min": 800.0,
            "max": 4200.0
        },
        {
            "current": 4201.235,
            "min": 800.0,
            "max": 4200.0
        },
        {
            "current": 3400.0,
            "min": 800.0,
            "max": 4200.0
        },
        {
            "current": 4201.651,
            "min": 800.0,
            "max": 4200.0
        }
    ],
    "disk": {
        "/": {
            "total": 3665.956069946289,
            "used": 2254.563320159912
        }
    },
    "gpu": "NVIDIA RTX A4000",
    "gpu_count": 1,
    "gpu_devices": [
        {
            "name": "NVIDIA RTX A4000",
            "memory_total": 17171480576
        }
    ],
    "memory": {
        "total": 125.55233764648438
    }
}
